werewolf/__about__.py
werewolf/__init__.py
werewolf-0.0.1.dist-info/METADATA
werewolf-0.0.1.dist-info/WHEEL
werewolf-0.0.1.dist-info/licenses/LICENSE.txt
werewolf-0.0.1.dist-info/RECORD
